{
  "status": "ready_for_integration",
  "total_files_analyzed": 37,
  "pages_found": 9,
  "components_found": 13,
  "steps": [
    "1. Импортировать design-tokens/variables.css в основной CSS/SCSS файл",
    "2. Создать React компоненты на основе анализа",
    "3. Применить стили из design-tokens к компонентам",
    "4. Заменить существующие компоненты на новые, стилизованные",
    "5. Проверить адаптивность и кроссбраузерность",
    "6. Протестировать все интерактивные элементы"
  ],
  "estimated_time": "3-4 weeks (35 screenshots analyzed)",
  "pages_to_implement": [
    "additional_image3",
    "page_2",
    "page_1",
    "homepage",
    "page_5",
    "page_6",
    "page_4",
    "additional_image2",
    "additional_image4"
  ],
  "components_to_implement": [
    "Breadcrumbs",
    "Dropdown",
    "CarCard",
    "DealershipCard",
    "Pagination",
    "SearchBar",
    "Modal",
    "Gallery",
    "Accordion",
    "Tooltip",
    "FilterPanel",
    "Slider",
    "Tabs"
  ],
  "priority_components": [
    "Header",
    "HeroSection",
    "CarCard",
    "FilterPanel",
    "SearchBar",
    "Pagination",
    "Modal",
    "Button"
  ]
}